ckanext/__init__.py
ckanext/clamav/__init__.py
ckanext/clamav/adapters.py
ckanext/clamav/config.py
ckanext/clamav/plugin.py
ckanext/clamav/utils.py
ckanext/clamav/tests/__init__.py
ckanext/clamav/tests/test_plugin.py
ckanext_clamav-1.0.32.dist-info/LICENSE
ckanext_clamav-1.0.32.dist-info/METADATA
ckanext_clamav-1.0.32.dist-info/WHEEL
ckanext_clamav-1.0.32.dist-info/entry_points.txt
ckanext_clamav-1.0.32.dist-info/top_level.txt
ckanext_clamav-1.0.32.dist-info/RECORD
