Metadata-Version: 2.1
Name: ckanext-clamav
Version: 1.0.32
Summary: Check upload resources for viruses
Author-email: DataShades <datashades@linkdigital.com.au>, Oleksandr Cherniavskyi <mutantsan@gmail.com>
Maintainer-email: DataShades <datashades@linkdigital.com.au>
License: AGPL
Project-URL: Homepage, https://github.com/DataShades/ckanext-clamav
Classifier: Development Status :: 5 - Production/Stable
Classifier: License :: OSI Approved :: GNU Affero General Public License v3 or later (AGPLv3+)
Classifier: Programming Language :: Python
Classifier: Programming Language :: Python :: 3.9
Classifier: Programming Language :: Python :: 3.8
Requires-Python: >=3.8
License-File: LICENSE
